{"stat.craftItem.69":64,"stat.craftItem.102":240,"stat.craftItem.345":1,"stat.craftItem.61":17,"stat.leaveGame":2,"stat.craftItem.339":9,"stat.mineBlock.14":5,"stat.mineBlock.13":4,"stat.mineBlock.16":236,"stat.mineBlock.15":39,"stat.mineBlock.18":32,"stat.mineBlock.17":9,"stat.swimOneCm":74452,"stat.climbOneCm":2887,"stat.craftItem.76":2,"stat.mineBlock.145":2,"achievement.exploreAllBiomes":{"value":0,"progress":["ForestHills","Desert M","Flower Forest","Beach","Ice Plains","Cold Beach","Forest","River","Ocean","Desert","Savanna M","Extreme Hills","Deep Ocean","Hell","Savanna","Ice Mountains"]},"stat.mineBlock.12":214,"stat.craftItem.361":912,"stat.useItem.331":14,"stat.entityKilledBy.Spider":1,"stat.useItem.338":37,"stat.craftItem.89":16,"stat.mineBlock.4":35,"stat.mineBlock.110":1,"stat.mineBlock.5":9,"stat.mineBlock.3":327,"stat.mineBlock.1":416,"stat.mineBlock.112":5,"stat.mineBlock.113":2,"stat.craftItem.359":1,"stat.flyOneCm":2516090,"stat.useItem.102":1,"achievement.woodenGear":33,"stat.craftItem.22":7,"stat.useItem.323":1,"stat.craftItem.33":46,"achievement.mineWood":9,"stat.useItem.87":102,"stat.useItem.88":4,"stat.useItem.89":1,"stat.useItem.82":40,"achievement.openInventory":1323,"stat.craftItem.42":30,"stat.breakItem.275":1,"stat.useItem.81":15,"stat.mineBlock.154":3,"stat.deaths":55,"stat.drop":873,"stat.playOneMinute":3625550,"stat.craftItem.50":32,"stat.craftItem.54":39,"stat.killEntity.Zombie":3,"stat.diveOneCm":312210,"stat.breakItem.257":1,"stat.mineBlock.81":53,"stat.mineBlock.82":40,"stat.mineBlock.87":679,"stat.useItem.69":59,"stat.mineBlock.89":312,"stat.mineBlock.88":60,"stat.craftItem.173":166,"stat.useItem.76":4,"stat.jump":912,"stat.fallOneCm":807251,"stat.mineBlock.69":26,"stat.craftItem.5":872,"stat.damageTaken":-2147390272,"stat.useItem.49":35,"stat.useItem.54":12,"stat.useItem.50":104,"stat.damageDealt":2075,"stat.mineBlock.73":43,"stat.mineBlock.76":4,"stat.mineBlock.78":2,"stat.useItem.20":4,"stat.mineBlock.49":2,"stat.craftItem.263":27,"stat.useItem.275":76,"stat.useItem.154":10,"stat.walkOneCm":4267253,"stat.craftItem.265":59,"stat.craftItem.258":2,"stat.useItem.24":17,"achievement.redstoneEngine":16,"stat.mineBlock.50":5,"stat.mineBlock.54":2,"stat.useItem.38":7,"stat.mineBlock.24":90,"stat.useItem.257":236,"stat.useItem.259":1,"stat.craftItem.280":264,"stat.killEntity.Spider":4,"stat.mobKills":8,"stat.mineBlock.21":8,"stat.mineBlock.20":2,"stat.craftItem.152":6,"stat.craftItem.395":1,"stat.useItem.12":204,"stat.craftItem.154":9,"stat.useItem.145":2,"stat.mineBlock.39":12,"stat.useItem.1":1,"stat.useItem.4":141,"stat.useItem.5":9,"stat.useItem.3":222,"stat.useItem.17":1,"stat.useItem.13":1,"stat.mineBlock.31":4}